hkgfinder/__init__.py
hkgfinder/cli.py
hkgfinder/hkgfinder.hmm
hkgfinder/hkgfinder.py
hkgfinder/hkglib.py
hkgfinder-0.3.0.dist-info/LICENSE
hkgfinder-0.3.0.dist-info/entry_points.txt
hkgfinder-0.3.0.dist-info/WHEEL
hkgfinder-0.3.0.dist-info/METADATA
hkgfinder-0.3.0.dist-info/RECORD
