Metadata-Version: 2.1
Name: hkgfinder
Version: 0.3.0
Summary: find housekeeping genes in prokaryotic (meta)genomic data
Home-page: https://github.com/Ebedthan/hkgfinder
License: MIT
Keywords: bioinformatics
Author: Anicet Ebou
Author-email: anicet.ebou@gmail.com
Requires-Python: >=3.8,<4.0
Classifier: Development Status :: 5 - Production/Stable
Classifier: Intended Audience :: Developers
Classifier: Intended Audience :: Education
Classifier: Intended Audience :: Science/Research
Classifier: License :: OSI Approved :: GNU General Public License v3 (GPLv3)
Classifier: License :: OSI Approved :: MIT License
Classifier: Natural Language :: English
Classifier: Operating System :: Microsoft :: Windows
Classifier: Operating System :: POSIX :: Linux
Classifier: Operating System :: Unix
Classifier: Programming Language :: Python :: 3
Classifier: Programming Language :: Python :: 3.8
Classifier: Programming Language :: Python :: 3.9
Classifier: Programming Language :: Python :: 3.10
Classifier: Programming Language :: Python :: 3.11
Classifier: Programming Language :: Python :: 3.10
Classifier: Programming Language :: Python :: 3.8
Classifier: Programming Language :: Python :: 3.9
Classifier: Topic :: Scientific/Engineering :: Bio-Informatics
Requires-Dist: bio (>=1.3.9,<2.0.0)
Requires-Dist: pyfastx (>=0.8.4,<0.9.0)
Requires-Dist: pyhmmer (>=0.8.0,<0.9.0)
Requires-Dist: pyrodigal (>=2.1.0,<3.0.0)
Requires-Dist: xphyle (>=4.4.2,<5.0.0)
Project-URL: Documentation, https://github.com/Ebedthan/hkgfinder
Project-URL: Repository, https://github.com/Ebedthan/hkgfinder
